{
  "url": "https://api.open5e.com/v2/spells/deepmx_ley-leech/",
  "document": {
    "name": "Deep Magic Extended",
    "key": "deepmx",
    "type": "SOURCE",
    "display_name": "Deep Magic Extended",
    "publisher": {
      "name": "Kobold Press",
      "key": "kobold-press",
      "url": "https://api.open5e.com/v2/publishers/kobold-press/"
    },
    "gamesystem": {
      "name": "5th Edition 2014",
      "key": "5e-2014",
      "url": "https://api.open5e.com/v2/gamesystems/5e-2014/"
    },
    "permalink": "https://koboldpress.com/deepmagic"
  },
  "key": "deepmx_ley-leech",
  "casting_options": [
    {
      "type": "default",
      "damage_roll": null,
      "target_count": null,
      "duration": null,
      "range": null,
      "concentration": null,
      "shape_size": null,
      "desc": null
    },
    {
      "type": "slot_level_6",
      "damage_roll": "9d10",
      "target_count": null,
      "duration": null,
      "range": null,
      "concentration": null,
      "shape_size": null,
      "desc": null
    },
    {
      "type": "slot_level_7",
      "damage_roll": "10d10",
      "target_count": null,
      "duration": null,
      "range": null,
      "concentration": null,
      "shape_size": null,
      "desc": null
    },
    {
      "type": "slot_level_8",
      "damage_roll": "11d10",
      "target_count": null,
      "duration": null,
      "range": null,
      "concentration": null,
      "shape_size": null,
      "desc": null
    },
    {
      "type": "slot_level_9",
      "damage_roll": "12d10",
      "target_count": null,
      "duration": null,
      "range": null,
      "concentration": null,
      "shape_size": null,
      "desc": null
    }
  ],
  "school": {
    "name": "Necromancy",
    "key": "necromancy",
    "url": "https://api.open5e.com/v2/spellschools/necromancy/"
  },
  "classes": [
    {
      "name": "Druid",
      "key": "srd_druid",
      "url": "https://api.open5e.com/v2/classes/srd_druid/"
    },
    {
      "name": "Warlock",
      "key": "srd_warlock",
      "url": "https://api.open5e.com/v2/classes/srd_warlock/"
    },
    {
      "name": "Wizard",
      "key": "srd_wizard",
      "url": "https://api.open5e.com/v2/classes/srd_wizard/"
    }
  ],
  "range_unit": "feet",
  "shape_size_unit": "feet",
  "name": "Ley Leech",
  "desc": "You channel destructive ley energy through your touch. Make a melee spell attack against a creature within your reach. The target takes 8d10 necrotic damage and must succeed on a Constitution saving throw or have disadvantage on attack rolls, saving throws, and ability checks. An affected creature repeats the saving throw at the end of its turn, ending the effect on itself with a success. This spell has no effect against constructs or undead.",
  "level": 5,
  "higher_level": "When you cast this spell using a spell slot of 6th level or higher, the spell's damage increases by 1d10 for each slot level above 5th.",
  "target_type": "creature",
  "range_text": "Touch",
  "range": 0.1,
  "ritual": false,
  "casting_time": "action",
  "reaction_condition": null,
  "verbal": true,
  "somatic": true,
  "material": false,
  "material_specified": "",
  "material_cost": null,
  "material_consumed": false,
  "target_count": 1,
  "saving_throw_ability": "constitution",
  "attack_roll": true,
  "damage_roll": "8d10",
  "damage_types": [
    "necrotic"
  ],
  "duration": "instantaneous",
  "shape_type": null,
  "shape_size": null,
  "concentration": false
}