{
  "url": "https://api.open5e.com/v2/spells/deepm_broken-charge/",
  "document": {
    "name": "Deep Magic for 5th Edition",
    "key": "deepm",
    "type": "SOURCE",
    "display_name": "Deep Magic for 5th Edition",
    "publisher": {
      "name": "Kobold Press",
      "key": "kobold-press",
      "url": "https://api.open5e.com/v2/publishers/kobold-press/"
    },
    "gamesystem": {
      "name": "5th Edition 2014",
      "key": "5e-2014",
      "url": "https://api.open5e.com/v2/gamesystems/5e-2014/"
    },
    "permalink": "https://koboldpress.com/kpstore/product/deep-magic-for-5th-edition-hardcover/"
  },
  "key": "deepm_broken-charge",
  "casting_options": [
    {
      "type": "default",
      "damage_roll": null,
      "target_count": null,
      "duration": null,
      "range": null,
      "concentration": null,
      "shape_size": null,
      "desc": null
    },
    {
      "type": "slot_level_2",
      "damage_roll": null,
      "target_count": null,
      "duration": null,
      "range": null,
      "concentration": null,
      "shape_size": null,
      "desc": null
    },
    {
      "type": "slot_level_3",
      "damage_roll": null,
      "target_count": null,
      "duration": null,
      "range": null,
      "concentration": null,
      "shape_size": null,
      "desc": null
    },
    {
      "type": "slot_level_4",
      "damage_roll": null,
      "target_count": null,
      "duration": null,
      "range": null,
      "concentration": null,
      "shape_size": null,
      "desc": null
    },
    {
      "type": "slot_level_5",
      "damage_roll": null,
      "target_count": null,
      "duration": null,
      "range": null,
      "concentration": null,
      "shape_size": null,
      "desc": null
    },
    {
      "type": "slot_level_6",
      "damage_roll": null,
      "target_count": null,
      "duration": null,
      "range": null,
      "concentration": null,
      "shape_size": null,
      "desc": null
    },
    {
      "type": "slot_level_7",
      "damage_roll": null,
      "target_count": null,
      "duration": null,
      "range": null,
      "concentration": null,
      "shape_size": null,
      "desc": null
    },
    {
      "type": "slot_level_8",
      "damage_roll": null,
      "target_count": null,
      "duration": null,
      "range": null,
      "concentration": null,
      "shape_size": null,
      "desc": null
    },
    {
      "type": "slot_level_9",
      "damage_roll": null,
      "target_count": null,
      "duration": null,
      "range": null,
      "concentration": null,
      "shape_size": null,
      "desc": null
    }
  ],
  "school": {
    "name": "Enchantment",
    "key": "enchantment",
    "url": "https://api.open5e.com/v2/spellschools/enchantment/"
  },
  "classes": [],
  "range_unit": "feet",
  "shape_size_unit": "feet",
  "name": "Broken Charge",
  "desc": "When an enemy that you can see moves to within 5 feet of you, you utter a perplexing word that alters the foe’s course. The enemy must make a successful Wisdom saving throw or take 2d4 psychic damage and use the remainder of its speed to move in a direction of your choosing.\n",
  "level": 1,
  "higher_level": "When you cast this spell using a spell slot of 2nd level or higher, the target takes an additional 2d4 psychic damage for each slot level above 1st.",
  "target_type": "creature",
  "range_text": "10 feet",
  "range": 10,
  "ritual": false,
  "casting_time": "reaction",
  "reaction_condition": "which you take when an enemy approaches to within 5 feet of you",
  "verbal": true,
  "somatic": false,
  "material": false,
  "material_specified": "",
  "material_cost": null,
  "material_consumed": false,
  "target_count": 1,
  "saving_throw_ability": "wisdom",
  "attack_roll": false,
  "damage_roll": "",
  "damage_types": [],
  "duration": "instantaneous",
  "shape_type": null,
  "shape_size": null,
  "concentration": false
}