{
  "url": "https://api.open5e.com/v2/spells/deepm_harrying-hounds/",
  "document": {
    "name": "Deep Magic for 5th Edition",
    "key": "deepm",
    "type": "SOURCE",
    "display_name": "Deep Magic for 5th Edition",
    "publisher": {
      "name": "Kobold Press",
      "key": "kobold-press",
      "url": "https://api.open5e.com/v2/publishers/kobold-press/"
    },
    "gamesystem": {
      "name": "5th Edition 2014",
      "key": "5e-2014",
      "url": "https://api.open5e.com/v2/gamesystems/5e-2014/"
    },
    "permalink": "https://koboldpress.com/kpstore/product/deep-magic-for-5th-edition-hardcover/"
  },
  "key": "deepm_harrying-hounds",
  "casting_options": [
    {
      "type": "default",
      "damage_roll": null,
      "target_count": null,
      "duration": null,
      "range": null,
      "concentration": null,
      "shape_size": null,
      "desc": null
    },
    {
      "type": "slot_level_6",
      "damage_roll": null,
      "target_count": null,
      "duration": "12 hours",
      "range": null,
      "concentration": null,
      "shape_size": null,
      "desc": null
    },
    {
      "type": "slot_level_7",
      "damage_roll": null,
      "target_count": null,
      "duration": "16 hours",
      "range": null,
      "concentration": null,
      "shape_size": null,
      "desc": null
    },
    {
      "type": "slot_level_8",
      "damage_roll": null,
      "target_count": null,
      "duration": "20 hours",
      "range": null,
      "concentration": null,
      "shape_size": null,
      "desc": null
    },
    {
      "type": "slot_level_9",
      "damage_roll": null,
      "target_count": null,
      "duration": "24 hours",
      "range": null,
      "concentration": null,
      "shape_size": null,
      "desc": null
    }
  ],
  "school": {
    "name": "Enchantment",
    "key": "enchantment",
    "url": "https://api.open5e.com/v2/spellschools/enchantment/"
  },
  "classes": [],
  "range_unit": "feet",
  "shape_size_unit": "feet",
  "name": "Harrying Hounds",
  "desc": "When you cast this spell, choose a direction (north, south, northeast, or the like). Each creature in a 20-foot-radius sphere centered on a point you choose within range must succeed on a Wisdom saving throw when you cast this spell or be affected by it. When an affected creature travels, it travels at a fast pace in the opposite direction of the direction you chose as it believes a pack of dogs or wolves follows it from the chosen direction.\n  When an affected creature isn't traveling, it is frightened of your chosen direction. The affected creature occasionally hears howls or sees glowing eyes in the darkness at the edge of its vision in that direction. An affected creature will not stop at a destination, instead pacing half-circles around the destination until the effect ends, terrified the pack will overcome it if it stops moving.\n  An affected creature can make a Wisdom saving throw at the end of each 4-hour period, ending the effect on itself on a success. An affected creature moves along the safest available route unless it has nowhere to move, such as if it arrives at the edge of a cliff. When an affected creature can't safely move in the opposite direction of your chosen direction, it cowers in place, defending itself from hostile creatures but otherwise taking no actions. In such circumstances, the affected creature can repeat the saving throw every minute, ending the effect on itself on a success. The spell's effect is suspended when an affected creature is engaged in combat, allowing it to move as necessary to face hostile creatures.",
  "level": 5,
  "higher_level": "When you cast this spell using a spell slot of 6th level or higher, the duration increases by 4 hours for each slot level above 5th. If an affected creature travels for more than 8 hours, it risks exhaustion as if on a forced march.",
  "target_type": "creature",
  "range_text": "180 feet",
  "range": 180,
  "ritual": false,
  "casting_time": "action",
  "reaction_condition": null,
  "verbal": true,
  "somatic": true,
  "material": true,
  "material_specified": "a tuft of fur from a hunting dog",
  "material_cost": null,
  "material_consumed": false,
  "target_count": 1,
  "saving_throw_ability": "wisdom",
  "attack_roll": false,
  "damage_roll": "",
  "damage_types": [],
  "duration": "8 hours",
  "shape_type": "sphere",
  "shape_size": 20,
  "concentration": false
}