{
  "url": "https://api.open5e.com/v2/spells/deepm_fey-crown/",
  "document": {
    "name": "Deep Magic for 5th Edition",
    "key": "deepm",
    "type": "SOURCE",
    "display_name": "Deep Magic for 5th Edition",
    "publisher": {
      "name": "Kobold Press",
      "key": "kobold-press",
      "url": "https://api.open5e.com/v2/publishers/kobold-press/"
    },
    "gamesystem": {
      "name": "5th Edition 2014",
      "key": "5e-2014",
      "url": "https://api.open5e.com/v2/gamesystems/5e-2014/"
    },
    "permalink": "https://koboldpress.com/kpstore/product/deep-magic-for-5th-edition-hardcover/"
  },
  "key": "deepm_fey-crown",
  "casting_options": [
    {
      "type": "default",
      "damage_roll": null,
      "target_count": null,
      "duration": null,
      "range": null,
      "concentration": null,
      "shape_size": null,
      "desc": null
    },
    {
      "type": "slot_level_6",
      "damage_roll": null,
      "target_count": null,
      "duration": null,
      "range": null,
      "concentration": null,
      "shape_size": null,
      "desc": null
    },
    {
      "type": "slot_level_7",
      "damage_roll": null,
      "target_count": null,
      "duration": null,
      "range": null,
      "concentration": null,
      "shape_size": null,
      "desc": null
    },
    {
      "type": "slot_level_8",
      "damage_roll": null,
      "target_count": null,
      "duration": null,
      "range": null,
      "concentration": null,
      "shape_size": null,
      "desc": null
    },
    {
      "type": "slot_level_9",
      "damage_roll": null,
      "target_count": null,
      "duration": null,
      "range": null,
      "concentration": null,
      "shape_size": null,
      "desc": null
    }
  ],
  "school": {
    "name": "Abjuration",
    "key": "abjuration",
    "url": "https://api.open5e.com/v2/spellschools/abjuration/"
  },
  "classes": [],
  "range_unit": "feet",
  "shape_size_unit": "feet",
  "name": "Fey Crown",
  "desc": "By channeling the ancient wards of the Seelie Court, you create a crown of five flowers on your head. While wearing this crown, you have advantage on saving throws against spells and other magical effects and are immune to being charmed. As a bonus action, you can choose a creature within 30 feet of you (including yourself). Until the end of its next turn, the chosen creature is invisible and has advantage on saving throws against spells and other magical effects. Each time a chosen creature becomes invisible, one of the blossoms in the crown closes. After the last of the blossoms closes, the spell ends at the start of your next turn and the crown disappears.\n",
  "level": 5,
  "higher_level": "When you cast this spell using a spell slot of 6th level or higher, the crown can have one additional flower for each slot level above 5th. One additional flower is required as a material component for each additional flower in the crown.",
  "target_type": "creature",
  "range_text": "Self",
  "range": 0,
  "ritual": false,
  "casting_time": "action",
  "reaction_condition": null,
  "verbal": true,
  "somatic": true,
  "material": true,
  "material_specified": "five flowers of different colors",
  "material_cost": null,
  "material_consumed": false,
  "target_count": 1,
  "saving_throw_ability": "",
  "attack_roll": false,
  "damage_roll": "",
  "damage_types": [],
  "duration": "1 hour",
  "shape_type": null,
  "shape_size": null,
  "concentration": false
}