{
  "url": "https://api.open5e.com/v2/spells/srd-2024_resurrection/",
  "document": {
    "name": "System Reference Document 5.2",
    "key": "srd-2024",
    "type": "SOURCE",
    "display_name": "5e 2024 Rules",
    "publisher": {
      "name": "Wizards of the Coast",
      "key": "wizards-of-the-coast",
      "url": "https://api.open5e.com/v2/publishers/wizards-of-the-coast/"
    },
    "gamesystem": {
      "name": "5th Edition 2024",
      "key": "5e-2024",
      "url": "https://api.open5e.com/v2/gamesystems/5e-2024/"
    },
    "permalink": "https://dnd.wizards.com/resources/systems-reference-document"
  },
  "key": "srd-2024_resurrection",
  "casting_options": [],
  "school": {
    "name": "Necromancy",
    "key": "necromancy",
    "url": "https://api.open5e.com/v2/spellschools/necromancy/"
  },
  "classes": [
    {
      "name": "Bard",
      "key": "srd-2024_bard",
      "url": "https://api.open5e.com/v2/classes/srd-2024_bard/"
    },
    {
      "name": "Cleric",
      "key": "srd-2024_cleric",
      "url": "https://api.open5e.com/v2/classes/srd-2024_cleric/"
    }
  ],
  "range_unit": "feet",
  "shape_size_unit": "feet",
  "name": "Resurrection",
  "desc": "With a touch, you revive a dead creature that has been dead for no more than a century, didn't die of old age, and wasn't Undead when it died. The creature returns to life with all its Hit Points. This spell also neutralizes any poisons that affected the creature at the time of death. This spell closes all mortal wounds and restores any missing body parts. Coming back from the dead is an ordeal. The target takes a −4 penalty to D20 Tests. Every time the target finishes a Long Rest, the penalty is reduced by 1 until it becomes 0. Casting this spell to revive a creature that has been dead for 365 days or longer taxes you. Until you finish a Long Rest, you can't cast spells again, and you have Disadvantage on D20 Tests.",
  "level": 7,
  "higher_level": "",
  "target_type": "creature",
  "range_text": "Touch",
  "range": 0,
  "ritual": false,
  "casting_time": "hour",
  "reaction_condition": null,
  "verbal": true,
  "somatic": true,
  "material": true,
  "material_specified": "a diamond worth 1,000+ GP, which the spell consumes",
  "material_cost": null,
  "material_consumed": true,
  "target_count": 1,
  "saving_throw_ability": "",
  "attack_roll": false,
  "damage_roll": "",
  "damage_types": [],
  "duration": "instantaneous",
  "shape_type": null,
  "shape_size": null,
  "concentration": false
}