{
  "url": "https://api.open5e.com/v2/spells/toh_beast-within/",
  "document": {
    "name": "Tome of Heroes",
    "key": "toh",
    "type": "SOURCE",
    "display_name": "Tome of Heroes",
    "publisher": {
      "name": "Kobold Press",
      "key": "kobold-press",
      "url": "https://api.open5e.com/v2/publishers/kobold-press/"
    },
    "gamesystem": {
      "name": "5th Edition 2014",
      "key": "5e-2014",
      "url": "https://api.open5e.com/v2/gamesystems/5e-2014/"
    },
    "permalink": "https://koboldpress.com/kpstore/product/tome-of-heroes-for-5th-edition/"
  },
  "key": "toh_beast-within",
  "casting_options": [
    {
      "type": "default",
      "damage_roll": null,
      "target_count": null,
      "duration": null,
      "range": null,
      "concentration": null,
      "shape_size": null,
      "desc": null
    },
    {
      "type": "slot_level_5",
      "damage_roll": null,
      "target_count": 2,
      "duration": null,
      "range": null,
      "concentration": null,
      "shape_size": null,
      "desc": null
    },
    {
      "type": "slot_level_6",
      "damage_roll": null,
      "target_count": 3,
      "duration": null,
      "range": null,
      "concentration": null,
      "shape_size": null,
      "desc": null
    },
    {
      "type": "slot_level_7",
      "damage_roll": null,
      "target_count": 4,
      "duration": null,
      "range": null,
      "concentration": null,
      "shape_size": null,
      "desc": null
    },
    {
      "type": "slot_level_8",
      "damage_roll": null,
      "target_count": 5,
      "duration": null,
      "range": null,
      "concentration": null,
      "shape_size": null,
      "desc": null
    },
    {
      "type": "slot_level_9",
      "damage_roll": null,
      "target_count": 6,
      "duration": null,
      "range": null,
      "concentration": null,
      "shape_size": null,
      "desc": null
    }
  ],
  "school": {
    "name": "Transmutation",
    "key": "transmutation",
    "url": "https://api.open5e.com/v2/spellschools/transmutation/"
  },
  "classes": [],
  "range_unit": "feet",
  "shape_size_unit": "feet",
  "name": "Beast Within",
  "desc": "You imbue a willing creature with a touch of lycanthropy. The target gains a few bestial qualities appropriate to the type of lycanthrope you choose, such as tufts of fur, elongated claws, a fang-lined maw or tusks, and similar features. For the duration, the target has resistance to bludgeoning, piercing, and slashing damage from nonmagical attacks that aren't silvered. In addition, the target has advantage on Wisdom (Perception) checks that rely on hearing or smell. Finally, the creature can use its new claws and jaw or tusks to make unarmed strikes. The claws deal slashing damage equal to 1d4 + the target's Strength modifier on a hit. The bite deals piercing damage equal to 1d6 + the target's Strength modifier on a hit. The target's bite doesn't inflict lycanthropy.",
  "level": 4,
  "higher_level": "When you cast this spell using a spell slot of 5th level or higher, you can target one additional creature for each spell slot above 4th.",
  "target_type": "creature",
  "range_text": "30 feet",
  "range": 30,
  "ritual": false,
  "casting_time": "round",
  "reaction_condition": null,
  "verbal": true,
  "somatic": true,
  "material": true,
  "material_specified": "",
  "material_cost": null,
  "material_consumed": false,
  "target_count": 1,
  "saving_throw_ability": "",
  "attack_roll": false,
  "damage_roll": "",
  "damage_types": [],
  "duration": "1 hour",
  "shape_type": null,
  "shape_size": null,
  "concentration": true
}